README.rst
setup.py
uperation_base/__init__.py
uperation_base/operation_types/__init__.py
uperation_base/operation_types/access_token_operation/__init__.py
uperation_base/operation_types/command_operation/__init__.py
uperation_base/operation_types/docker_operation/__init__.py
uperation_base/operation_types/dot_env_operation/__init__.py
uperation_base/operation_types/json_operation/__init__.py
uperation_base/operation_types/log_operation/__init__.py
uperation_base/operation_types/yml_config_operation/__init__.py
uperation_base/operations/__init__.py
uperation_base/operations/command/__init__.py
uperation_base/operations/dockerfile/__init__.py
uperation_base/operations/dockerfile/resources/Dockerfile
uperation_base/operations/list_operation/__init__.py
uperation_base/operations/make_event/__init__.py
uperation_base/operations/make_library/__init__.py
uperation_base/operations/make_observer/__init__.py
uperation_base/operations/make_operation/__init__.py
uperation_base/operations/make_operationtype/__init__.py
uperation_base/operations/publish/__init__.py
uperation_base/operations/test/__init__.py
uperation_base/operations/utils/__init__.py
uperation_base/operations/utils/_test_utils.py
uperation_base/operations/utils/templates/__init__.py
uperation_base/operations/utils/templates/make_library/__init__.py
uperation_base/operations/utils/templates/make_library/setup.py
uperation_base/operations/utils/templates/make_library/make_library/__init__.py
uperation_base/operations/utils/templates/make_observer/__init__.py
uperation_base/operations/utils/templates/make_operation/__init__.py
uperation_base/operations/utils/templates/make_operation_type/__init__.py
uperation_base/operations/yaml_to_json/__init__.py
uperations_base.egg-info/PKG-INFO
uperations_base.egg-info/SOURCES.txt
uperations_base.egg-info/dependency_links.txt
uperations_base.egg-info/requires.txt
uperations_base.egg-info/top_level.txt