Metadata-Version: 1.0
Name: uperations-base
Version: 0.0.21
Summary: UNKNOWN
Home-page: https://github.com/baminou/Uperations-Base
Author: Brice Aminou
Author-email: brice.aminou@gmail.com
License: Creative Commons Attribution-Noncommercial-Share Alike license
Keywords: workflow tool
Platform: UNKNOWN
